{
    "id": 120357632,
    "name": "consistency challenge",
    "author": "stratonymous",
    "creators": ["stratonymous"],
    "verifier": "Stratonymous",
    "verification": "https://www.youtube.com/watch?v=XVkRzenV3aI",
    "percentToQualify": "100",
    "fps": "60-240",
	"version": "2.2",
    "records": [
	    {
		    "user": "galbeni7",
		    "link": "https://www.youtube.com/watch?v=XzjlB1vHnb4",
		    "hz": "CBF",
		    "percent": 100
	    },
        {
            "user": "Skibirizz",
            "link": "https://youtu.be/LEXHe6uxnBE?si=LaGxGDbNBmJkC_oy",
            "hz": "CBF",
            "percent": 100
        },
        {
            "user": "Saturn",
            "link": "https://media.discordapp.net/attachments/1365699473732276316/1381377681517707456/0608.mp4?ex=68474bb8&is=6845fa38&hm=d246de137cf8e8e7fc26f144a8d75c13b032ff428ed582d00d64830d9fe06e1d&",
            "hz": "144",
            "percent": 100
        },
        {
            "user": "ClawBuckle",
            "link": "https://youtu.be/wiHcrlGvzUA",
            "hz": "67",
            "percent": 100
        },
	    {
            "user": "Haruna",
            "link": "https://medal.tv/games/geometry-dash/clips/ksCFvMleYJrI-myVT?invite=cr-MSxQMHAsMzYwMzA5MzU1",
            "hz": "144",
            "percent": 100
        },
	    {
		    "user": "blightedcoconut",
		    "link": "https://www.youtube.com/watch?v=s9om4DJfDVY",
		    "hz": "CBF",
		    "percent": 100
	    },
	    {
		    "user": "Sadisyourlife",
		    "link": "https://www.youtube.com/watch?v=BZ1nVFdhuPk",
		    "hz": "240",
		    "percent": 100
	    },
	    {
		    "user": "Sol-XSL",
		    "link": "https://cdn.discordapp.com/attachments/1365699473732276316/1384225076898959382/Consistency_Challenge.mov?ex=6851a78f&is=6850560f&hm=a31e9f915805500c4ceaa74f434a4f9695a7da2dfa8e7899957077a52878a8f9&",
		    "hz": "CBF",
		    "percent": 100
	    },
	    {
		    "user": "Moderatepine",
		    "link": "https://cdn.discordapp.com/attachments/1365699473732276316/1384951786724393101/IMG_3695.mov?ex=68544c5d&is=6852fadd&hm=fcb6d28d26f293da03253fd4bbeaa30f9a1e335502a68b00acce42d630a44d2c&",
		    "hz": "CBF",
		    "percent": 100
	    },
	    {
		    "user": "MrDrool",
		    "link": "https://www.youtube.com/watch?v=tNwdBYSG-e0",
		    "hz": "240",
		    "percent": 100
	    },
	    {
		    "user": "inyostacm13",
		    "link": "https://cdn.discordapp.com/attachments/1365699473732276316/1386317113291051138/121.mp4?ex=685943ec&is=6857f26c&hm=87018308eaabc536503db6d0915d0ef836934428d432e94aa1a88c2e1fc42f14&",
		    "hz": "240",
		    "percent": 100
	    },
	    {
		    "user": "nensa",
		    "link": "https://cdn.discordapp.com/attachments/1365699473732276316/1386332393064894574/Replay_2025-06-22_22-43-54_-_Trim.mp4?ex=68595227&is=685800a7&hm=50bbaf4216c57d7fdbdcb13e6462f1c427295700d7f3f73a1ee11ae776f34f84&",
		    "hz": "CBF",
		    "percent": 100
	    }
    ]
}
