{
    "id": 69063603,
    "name": "for th3name",
    "author": "bluej167",
    "creators": [],
    "verifier": "bluej167",
    "verification": "https://www.youtube.com/watch?v=cTUmOzzPew8",
    "percentToQualify": "100",
    "fps": "60-360",
    "records": [
        {
        "user": "galbeni7",
        "link": "https://www.youtube.com/watch?v=cTUmOzzPew8",
        "hz": "CBF",
        "percent": 100
        },
        {
            "user": "blightedcoconut",
            "link": "https://www.youtube.com/watch?v=N8jzfzp30zY",
            "hz": "CBF",
            "percent": 100
        },
        {
            "user": "Frozix",
            "link": "https://www.youtube.com/watch?v=kyYChEVmM6I",
            "hz": "CBF",
            "percent": 100
        },
        {
            "user": "ad3usgmd",
            "link": "https://www.youtube.com/watch?v=eTJ1UYykrsw",
            "hz": "CBF",
            "percent": 100
        },
        {
            "user": "zWardott",
            "link": "https://www.youtube.com/watch?v=Qte89zvZ5uI",
            "hz": "CBF",
            "percent": 100
        },
        {
            "user": "aelzfr",
            "link": "https://www.youtube.com/watch?v=w1ZxohOf2IY",
            "hz": "240",
            "percent": 100
        },
        {
            "user": "GDSlaughter",
            "link": "https://www.youtube.com/watch?v=xFHisePlMFM",
            "hz": "240",
            "percent": 100
        },
        {
            "user": "gloosy",
            "link": "https://www.youtube.com/watch?v=WTuSvz--4SM",
            "hz": "CBF",
            "percent": 100,
            "mobile": "true"
        },
        {
            "user": "d0sU",
            "link": "https://www.youtube.com/watch?v=ec3rLmehBvQ",
            "hz": "CBF",
            "percent": 100,
            "mobile": "true"
        },
        {
            "user": "Olympix",
            "link": "https://www.youtube.com/watch?v=a_kpijI_Lgk",
            "hz": "CBF",
            "percent": 100
        },
        {
            "user": "Przemysław Woliński",
            "link": "https://www.youtube.com/watch?v=QXaWuL15arA",
            "hz": "CBF",
            "percent": 100
        },
        {
            "user": "dejid",
            "link": "https://www.youtube.com/watch?v=6YuQ_DuVrXU",
            "hz": "240",
            "percent": 100
        },
        {
            "user": "heitorfbd",
            "link": "https://youtu.be/c4nKZmNmne0",
            "hz": "60",
            "percent": 100
        },
        {
            "user": "dilmobe",
            "link": "https://youtu.be/gcwBVPDJP1M?si=pSooPSVHFdJxDHtL",
            "hz": "240",
            "percent": 100
        },
        {
            "user": "ItzQw4nt3r",
            "link": "https://youtu.be/8LBx8z9epmk?si=qnK7bdM__Q9vcnAR",
            "hz": "CBF",
            "percent": 100
        },
        {
            "user": "Sadisyourlife",
            "link": "https://youtu.be/vyPYwzvVBE4?si=Ym-K6iBwBpCjH0pd",
            "hz": "240",
            "percent": 100
        },
        {
            "user": "ZenosSins",
            "link": "https://media.discordapp.net/attachments/1365699473732276316/1371957659913293965/copy_8D3E3D56-0FD6-4D51-9B25-77CB27E28984.mov?ex=682506a3&is=6823b523&hm=7e0fb50ac25e831b840f4082ea79a76dbfc1162f0a200b6f9f7bdc02a4650c9e&",
            "hz": "CBF",
            "percent": 100,
            "mobile": "true"
        },
        {
            "user": "chillguy73",
            "link": "https://discord.com/channels/1342438507527802901/1365699473732276316/1373258754761424918",
            "hz": "CBF",
            "percent": 100
        },
        {
            "user": "Saturn",
            "link": "https://discord.com/channels/1342438507527802901/1365699473732276316/1373307243923116174",
            "hz": "144",
            "percent": 100
        },
        {
            "user": "pastel",
            "link": "https://www.youtube.com/watch?v=uGR8AMCL5s0",
            "hz": "180",
            "percent": 100
        },
        {
            "user": "felmix9",
            "link": "https://www.youtube.com/watch?v=Gc3WN32T3sg",
            "hz": "240",
            "percent": 100
        },
        {
            "user": "Angopr",
            "link": "https://www.youtube.com/watch?v=XH3w1p2hAQ8",
            "hz": "240",
            "percent": 100
        }
    ]
}
