{
    "id": 128925279,
    "name": "fourty six",
    "author": "Vantasia",
    "creators": [],
    "verifier": "Vantasia",
    "verification": "https://youtu.be/3FIx5bu-eoQ",
    "percentToQualify": "100",
    "fps": "240",
	"version": "2.2",
    "records": [
		{
			"user": "Luke",
			"link": "https://medal.tv/games/geometry-dash/clips/mEpmWyDkWJj10cdTI?invite=cr-MSwzc2YsMzAwMTE3NTc5&v=13",
			"hz": "CBF",
			"percent": 100
		},
		{
			"user": "tFluffy",
			"link": "https://cdn.discordapp.com/attachments/1365699473732276316/1510909834453586000/46.mp4?ex=6a1fd96f&is=6a1e87ef&hm=4f8c2b86092a98310feb75fb059a408b5cb08968a606ae3d51cc27900b7bcc74&",
			"hz": "CBF",
			"percent": 100
       	},
		{
           "user": "maxf",
           "link": "https://discord.com/channels/1342438507527802901/1365699473732276316/1516261164022104095",
           "hz": "CBF",
           "percent": 100
		}
    ]
}
