{
    "id": 71169967,
    "name": "QWERTYUIOP",
    "author": "Sorke",
    "creators": [],
    "verifier": "Sorke",
    "verification": "https://www.youtube.com/watch?v=cTUmOzzPew8",
    "percentToQualify": "100",
    "fps": "60-360",
    "records": [
        {
        "user": "galbeni7",
        "link": "https://www.youtube.com/watch?v=cTUmOzzPew8",
        "hz": "CBF",
        "percent": 100
        },
        {
            "user": "blightedcoconut",
            "link": "https://www.youtube.com/watch?v=u4-1ol9MHgA",
            "hz": "CBF",
            "percent": 100
        }
    ]
}
