{
    "id": 125562638,
    "name": "Swingsistency",
    "author": "Taublix",
    "creators": [],
    "verifier": "Taublix",
    "verification": "https://www.youtube.com/watch?v=wvosQtJk39Y",
    "percentToQualify": "100",
	"version": "2.2",
    "records": [
		{
            "user": "tFluffy",
            "link": "https://discord.com/channels/1342438507527802901/1365699473732276316/1434507175862079588",
            "hz": "240",
            "percent": 100
        },
		{
			"user": "spaceflame",
			"link": "https://youtu.be/qFqdFWK1TMQ",
			"hz": "240",
			"percent": 100
		},
		{
			"user": "midnight_luna",
			"link": "https://drive.google.com/file/d/1I-4SyRVGOarsdDvDqFoDM26S4uR1bR9r/view?usp=sharing",
			"hz": "CBF",
			"percent": 100
		}
    ]
}
