{
    "id": 118276087,
    "name": "wasurm but weird",
    "author": "blightedcoconut",
    "creators": [],
    "verifier": "blightedcoconut",
    "verification": "https://www.youtube.com/watch?v=URWkJQUAOYA",
    "percentToQualify": "100",
    "fps": "60-240",
    "version": "2.2",
    "records": [
        {
            "user": "ClawBuckle",
            "link": "https://youtu.be/jwdq_-2Oy7o?si=q7UFfMJbWSUucz3A",
            "hz": "240",
            "percent": 100
        },
        {
            "user": "ad3usgmd",
            "link": "https://youtu.be/wFFFi1WAwzY?si=C3aVn9t1u6OjciaV",
            "hz": "CBF",
            "percent": 100
        },
        {
            "user": "Sadisyourlife",
            "link": "https://youtu.be/9TwIWKzwCJ8?si=pmdDa230ciQphzZN",
            "hz": "240",
            "percent": 100
        },
        {
            "user": "Saturn",
            "link": "https://discord.com/channels/1342438507527802901/1365699473732276316/1373695806586093739",
            "hz": "144",
            "percent": 100
        },
        {
            "user": "FoldedZero",
            "link": "https://www.youtube.com/watch?v=LgWzGPmTS-E",
            "hz": "CBF",
            "percent": 100
        },
        {
            "user": "dejid",
            "link": "https://www.youtube.com/watch?v=G2pmPlCqqms",
            "hz": "240",
            "percent": 100
        },
        {
            "user": "galbeni7",
            "link": "https://www.youtube.com/watch?v=YrqnvJOdXE4",
            "hz": "CBF",
            "percent": 100
        },
        {
		    "user": "PureL",
		    "link": "https://www.youtube.com/watch?v=RqtAZQvxiXA",
		    "hz": "CBF",
		    "percent": 100
	    },
        {
            "user": "Skibirizz",
            "link": "https://youtu.be/xHrw4_0SEVs?si=StgyfnOUT77QOFKW",
            "hz": "CBF",
            "percent": 100
        },
        {
            "user": "Frozix",
            "link": "https://youtu.be/4fKwSpZnbyE?si=9RMhtw6vhBkhmdyP",
            "hz": "CBF",
            "percent": 100
        },
	    {
		    "user": "Zxentirix",
		    "link": "https://www.youtube.com/watch?v=9ZvJXv8nyUM",
		    "hz": "240",
		    "percent": 100
	    },
        {
            "user": "tubo",
            "link": "https://youtu.be/EAAaIlXppOI?si=64HXgyenzoN4iaWv",
            "hz": "240",
            "percent": 100
        },
	    {
		    "user": "leynest",
		    "link": "https://medal.tv/games/geometry-dash/clips/kqx7zRFtP5Er8RDuw?invite=cr-MSxZSzksNDA2MDA0NDg2",
		    "hz": "240",
		    "percent": 100
	    },
	    {
		    "user": "LinCalc",
		    "link": "https://cdn.discordapp.com/attachments/1365699473732276316/1380051847594639420/Geometry_Dash_2025.06.05_-_01.09.23.13.mp4?ex=684278f0&is=68412770&hm=3b0f826f70ef26bea7aa8772c315bfd7b484e59e7bbcb208c0cce996ac17215d&",
		    "hz": "CBF",
		    "percent": 100
	    },
	    {
		    "user": "inkstain",
		    "link": "https://cdn.discordapp.com/attachments/1365699473732276316/1380181148277407794/chalnges_i_beaten.mp4?ex=6842f15c&is=68419fdc&hm=9caa3d44b47b74a7e8d12a2b3798f754d056cb6da12aa891ee19127524be8be1&",
		    "hz": "240",
		    "percent": 100
	    },
	    {
		    "user": "Masterace30",
		    "link": "https://cdn.discordapp.com/attachments/1365699473732276316/1380620399129395281/Untitled_video_-_Made_with_Clipchamp_1.mp4?ex=68448a71&is=684338f1&hm=1c909f43580f049aea5ec14001b2e5f436fdad58079412fa8b268f50b5ad8a83&",
		    "hz": "CBF",
		    "percent": 100
	    },
	    {
		    "user": "kap1195",
		    "link": "https://youtu.be/Mmz2jbiwiB8",
		    "hz": "240",
		    "percent": 100
	    },
        {
            "user": "nensa",
            "link": "https://youtu.be/mYKzoZzQYz8?si=a_hYll7DWCSqYpm7",
            "hz": "CBF",
            "percent": 100
        },
	    {
		    "user": "Powerball20",
		    "link": "https://www.youtube.com/watch?v=gt6d0hEAK0c",
		    "hz": "CBF",
		    "percent": 100
	    },
	    {
		    "user": "May_XaX",
		    "link": "https://medal.tv/pl/games/geometry-dash/clips/kvGY25eR2jg9Nq0Bh?invite=cr-MSxINWIsMzg2Mzc3NzM0",
		    "hz": "240",
		    "percent": 100
	    },
	    {
		    "user": "Moderatepine",
		    "link": "https://cdn.discordapp.com/attachments/1365699473732276316/1384951686027673682/IMG_3700.mov?ex=68544c45&is=6852fac5&hm=fbd2b63b18d5ca549609bc32bfa0dc65d38f4560e5c9732ca206770a7c6e62fe&",
		    "hz": "CBF",
		    "percent": 100
	    }
    ]
}
